history/__init__.py
history/__main__.py
history/lang.py
history/scraper.py
article_history-1.0.1.dist-info/LICENSE
article_history-1.0.1.dist-info/METADATA
article_history-1.0.1.dist-info/WHEEL
article_history-1.0.1.dist-info/entry_points.txt
article_history-1.0.1.dist-info/top_level.txt
article_history-1.0.1.dist-info/RECORD
